chatmap_py-0.0.9.dist-info/METADATA
chatmap_py-0.0.9.dist-info/WHEEL
chatmap_py-0.0.9.dist-info/entry_points.txt
chatmap_py-0.0.9.dist-info/licenses/LICENSE
chatmap_py/__init__.py
chatmap_py/__version__.py
chatmap_py/chatmap.py
chatmap_py/cli.py
chatmap_py/parser.py
chatmap_py-0.0.9.dist-info/RECORD
