Metadata-Version: 2.1
Name: chatmap-py
Version: 0.0.9
Summary: Analyzes chat logs and pair locations with messages, generating a GeoJSON.
Keywords: hot,geojson,data,chat,chatmap
Author-Email: Emilio Mariscal <emilio.mariscal@hotosm.org>
License: AGPL-3.0-only
Classifier: Topic :: Utilities
Classifier: Topic :: Scientific/Engineering :: GIS
Classifier: Programming Language :: Python :: 3
Classifier: Programming Language :: Python :: 3.1
Project-URL: homepage, https://github.com/hotosm/chatmap/tree/master/chatmap-py
Project-URL: documentation, https://github.com/hotosm/chatmap/tree/master/chatmap-py
Project-URL: repository, https://github.com/hotosm/chatmap
Requires-Python: >=3.1
